smart_cache/__init__.py
smart_cache-1.0.3.dist-info/METADATA
smart_cache-1.0.3.dist-info/WHEEL
smart_cache-1.0.3.dist-info/top_level.txt
smart_cache-1.0.3.dist-info/RECORD
