Metadata-Version: 2.1
Name: smart_cache
Version: 1.0.3
Summary: Python caching library that is persistent and uses bytecode analysis to determine re-evaluation
Home-page: https://github.com/andrewgazelka/smart-cache
Author: Andrew Gazelka
Author-email: andrew.gazelka@gmail.com
License: MIT
Classifier: License :: OSI Approved :: MIT License
Classifier: Programming Language :: Python :: 3
Classifier: Programming Language :: Python :: 3.9
